{"name":"core\\src\\game\\economy\\industry\\catalog.rs","start_line":1,"end_line":152,"kind":"unit","spaces":[{"name":"IndustryCatalog","start_line":14,"end_line":61,"kind":"impl","spaces":[{"name":"load_from_dir","start_line":15,"end_line":44,"kind":"function","spaces":[{"name":"<anonymous>","start_line":32,"end_line":34,"kind":"function","spaces":[],"metrics":{"nargs":{"total_functions":0.0,"total_closures":0.0,"average_functions":0.0,"average_closures":0.0,"total":0.0,"average":0.0,"functions_min":0.0,"functions_max":0.0,"closures_min":0.0,"closures_max":0.0},"nexits":{"sum":0.0,"average":0.0,"min":0.0,"max":0.0},"cognitive":{"sum":0.0,"average":0.0,"min":0.0,"max":0.0},"cyclomatic":{"sum":1.0,"average":1.0,"min":1.0,"max":1.0},"halstead":{"n1":4.0,"N1":6.0,"n2":4.0,"N2":4.0,"length":10.0,"estimated_program_length":16.0,"purity_ratio":1.6,"vocabulary":8.0,"volume":30.0,"difficulty":2.0,"level":0.5,"effort":60.0,"time":3.3333333333333335,"bugs":0.005108729549290353},"loc":{"sloc":3.0,"ploc":3.0,"lloc":0.0,"cloc":0.0,"blank":0.0,"sloc_average":3.0,"ploc_average":3.0,"lloc_average":0.0,"cloc_average":0.0,"blank_average":0.0,"sloc_min":3.0,"sloc_max":3.0,"cloc_min":0.0,"cloc_max":0.0,"ploc_min":3.0,"ploc_max":3.0,"lloc_min":0.0,"lloc_max":0.0,"blank_min":0.0,"blank_max":0.0},"nom":{"functions":0.0,"closures":1.0,"functions_average":0.0,"closures_average":1.0,"total":1.0,"average":1.0,"functions_min":0.0,"functions_max":0.0,"closures_min":1.0,"closures_max":1.0},"mi":{"mi_original":135.2862545389334,"mi_sei":119.57777639115298,"mi_visual_studio":79.11476873621837},"abc":{"assignments":0.0,"branches":0.0,"conditions":0.0,"magnitude":0.0,"assignments_average":0.0,"branches_average":0.0,"conditions_average":0.0,"assignments_min":0.0,"assignments_max":0.0,"branches_min":0.0,"branches_max":0.0,"conditions_min":0.0,"conditions_max":0.0}}},{"name":"<anonymous>","start_line":35,"end_line":40,"kind":"function","spaces":[],"metrics":{"nargs":{"total_functions":0.0,"total_closures":0.0,"average_functions":0.0,"average_closures":0.0,"total":0.0,"average":0.0,"functions_min":0.0,"functions_max":0.0,"closures_min":0.0,"closures_max":0.0},"nexits":{"sum":0.0,"average":0.0,"min":0.0,"max":0.0},"cognitive":{"sum":0.0,"average":0.0,"min":0.0,"max":0.0},"cyclomatic":{"sum":1.0,"average":1.0,"min":1.0,"max":1.0},"halstead":{"n1":4.0,"N1":6.0,"n2":4.0,"N2":4.0,"length":10.0,"estimated_program_length":16.0,"purity_ratio":1.6,"vocabulary":8.0,"volume":30.0,"difficulty":2.0,"level":0.5,"effort":60.0,"time":3.3333333333333335,"bugs":0.005108729549290353},"loc":{"sloc":6.0,"ploc":6.0,"lloc":0.0,"cloc":0.0,"blank":0.0,"sloc_average":6.0,"ploc_average":6.0,"lloc_average":0.0,"cloc_average":0.0,"blank_average":0.0,"sloc_min":6.0,"sloc_max":6.0,"cloc_min":0.0,"cloc_max":0.0,"ploc_min":6.0,"ploc_max":6.0,"lloc_min":0.0,"lloc_max":0.0,"blank_min":0.0,"blank_max":0.0},"nom":{"functions":0.0,"closures":1.0,"functions_average":0.0,"closures_average":1.0,"total":1.0,"average":1.0,"functions_min":0.0,"functions_max":0.0,"closures_min":1.0,"closures_max":1.0},"mi":{"mi_original":124.0572702138623,"mi_sei":103.37777639115299,"mi_visual_studio":72.54811123617678},"abc":{"assignments":0.0,"branches":0.0,"conditions":0.0,"magnitude":0.0,"assignments_average":0.0,"branches_average":0.0,"conditions_average":0.0,"assignments_min":0.0,"assignments_max":0.0,"branches_min":0.0,"branches_max":0.0,"conditions_min":0.0,"conditions_max":0.0}}}],"metrics":{"nargs":{"total_functions":1.0,"total_closures":0.0,"average_functions":1.0,"average_closures":0.0,"total":1.0,"average":0.3333333333333333,"functions_min":0.0,"functions_max":1.0,"closures_min":0.0,"closures_max":0.0},"nexits":{"sum":2.0,"average":0.6666666666666666,"min":0.0,"max":2.0},"cognitive":{"sum":4.0,"average":1.3333333333333333,"min":0.0,"max":4.0},"cyclomatic":{"sum":11.0,"average":3.6666666666666665,"min":1.0,"max":9.0},"halstead":{"n1":20.0,"N1":90.0,"n2":26.0,"N2":46.0,"length":136.0,"estimated_program_length":208.64999456941564,"purity_ratio":1.5341911365398209,"vocabulary":46.0,"volume":751.2044260237537,"difficulty":17.692307692307693,"level":0.05652173913043478,"effort":13290.539845035644,"time":738.3633247242025,"bugs":0.1870282282833924},"loc":{"sloc":30.0,"ploc":29.0,"lloc":12.0,"cloc":0.0,"blank":1.0,"sloc_average":10.0,"ploc_average":9.666666666666666,"lloc_average":4.0,"cloc_average":0.0,"blank_average":0.3333333333333333,"sloc_min":3.0,"sloc_max":6.0,"cloc_min":0.0,"cloc_max":0.0,"ploc_min":3.0,"ploc_max":6.0,"lloc_min":0.0,"lloc_max":0.0,"blank_min":0.0,"blank_max":0.0},"nom":{"functions":1.0,"closures":2.0,"functions_average":0.3333333333333333,"closures_average":0.6666666666666666,"total":3.0,"average":1.0,"functions_min":0.0,"functions_max":1.0,"closures_min":0.0,"closures_max":1.0},"mi":{"mi_original":78.93787775403717,"mi_sei":39.302451235484966,"mi_visual_studio":46.162501610548055},"abc":{"assignments":0.0,"branches":0.0,"conditions":0.0,"magnitude":0.0,"assignments_average":0.0,"branches_average":0.0,"conditions_average":0.0,"assignments_min":0.0,"assignments_max":0.0,"branches_min":0.0,"branches_max":0.0,"conditions_min":0.0,"conditions_max":0.0}}},{"name":"from_embedded","start_line":46,"end_line":60,"kind":"function","spaces":[{"name":"<anonymous>","start_line":56,"end_line":56,"kind":"function","spaces":[],"metrics":{"nargs":{"total_functions":0.0,"total_closures":0.0,"average_functions":0.0,"average_closures":0.0,"total":0.0,"average":0.0,"functions_min":0.0,"functions_max":0.0,"closures_min":0.0,"closures_max":0.0},"nexits":{"sum":0.0,"average":0.0,"min":0.0,"max":0.0},"cognitive":{"sum":0.0,"average":0.0,"min":0.0,"max":0.0},"cyclomatic":{"sum":1.0,"average":1.0,"min":1.0,"max":1.0},"halstead":{"n1":3.0,"N1":4.0,"n2":3.0,"N2":3.0,"length":7.0,"estimated_program_length":9.509775004326936,"purity_ratio":1.3585392863324195,"vocabulary":6.0,"volume":18.094737505048094,"difficulty":1.5,"level":0.6666666666666666,"effort":27.14210625757214,"time":1.5078947920873411,"bugs":0.0030105171772436758},"loc":{"sloc":1.0,"ploc":1.0,"lloc":0.0,"cloc":0.0,"blank":0.0,"sloc_average":1.0,"ploc_average":1.0,"lloc_average":0.0,"cloc_average":0.0,"blank_average":0.0,"sloc_min":1.0,"sloc_max":1.0,"cloc_min":0.0,"cloc_max":0.0,"ploc_min":1.0,"ploc_max":1.0,"lloc_min":0.0,"lloc_max":0.0,"blank_min":0.0,"blank_max":0.0},"nom":{"functions":0.0,"closures":1.0,"functions_average":0.0,"closures_average":1.0,"total":1.0,"average":1.0,"functions_min":0.0,"functions_max":0.0,"closures_min":1.0,"closures_max":1.0},"mi":{"mi_original":155.7127700178179,"mi_sei":149.04700897518126,"mi_visual_studio":91.0600994256245},"abc":{"assignments":0.0,"branches":0.0,"conditions":0.0,"magnitude":0.0,"assignments_average":0.0,"branches_average":0.0,"conditions_average":0.0,"assignments_min":0.0,"assignments_max":0.0,"branches_min":0.0,"branches_max":0.0,"conditions_min":0.0,"conditions_max":0.0}}}],"metrics":{"nargs":{"total_functions":0.0,"total_closures":0.0,"average_functions":0.0,"average_closures":0.0,"total":0.0,"average":0.0,"functions_min":0.0,"functions_max":0.0,"closures_min":0.0,"closures_max":0.0},"nexits":{"sum":1.0,"average":0.5,"min":0.0,"max":1.0},"cognitive":{"sum":1.0,"average":0.5,"min":0.0,"max":1.0},"cyclomatic":{"sum":5.0,"average":2.5,"min":1.0,"max":4.0},"halstead":{"n1":18.0,"N1":51.0,"n2":24.0,"N2":31.0,"length":82.0,"estimated_program_length":185.09775004326934,"purity_ratio":2.2572896346740166,"vocabulary":42.0,"volume":442.1700286678584,"difficulty":11.625,"level":0.08602150537634409,"effort":5140.226583263854,"time":285.5681435146586,"bugs":0.09928117783035546},"loc":{"sloc":15.0,"ploc":15.0,"lloc":5.0,"cloc":0.0,"blank":0.0,"sloc_average":7.5,"ploc_average":7.5,"lloc_average":2.5,"cloc_average":0.0,"blank_average":0.0,"sloc_min":1.0,"sloc_max":1.0,"cloc_min":0.0,"cloc_max":0.0,"ploc_min":1.0,"ploc_max":1.0,"lloc_min":0.0,"lloc_max":0.0,"blank_min":0.0,"blank_max":0.0},"nom":{"functions":1.0,"closures":1.0,"functions_average":0.5,"closures_average":0.5,"total":2.0,"average":1.0,"functions_min":0.0,"functions_max":1.0,"closures_min":0.0,"closures_max":1.0},"mi":{"mi_original":94.30277540271771,"mi_sei":60.85839372057613,"mi_visual_studio":55.14782187293433},"abc":{"assignments":0.0,"branches":0.0,"conditions":0.0,"magnitude":0.0,"assignments_average":0.0,"branches_average":0.0,"conditions_average":0.0,"assignments_min":0.0,"assignments_max":0.0,"branches_min":0.0,"branches_max":0.0,"conditions_min":0.0,"conditions_max":0.0}}}],"metrics":{"nargs":{"total_functions":1.0,"total_closures":0.0,"average_functions":0.5,"average_closures":0.0,"total":1.0,"average":0.2,"functions_min":0.0,"functions_max":1.0,"closures_min":0.0,"closures_max":0.0},"nexits":{"sum":0.0,"average":0.6,"min":0.0,"max":2.0},"cognitive":{"sum":5.0,"average":1.0,"min":0.0,"max":4.0},"cyclomatic":{"sum":17.0,"average":2.8333333333333335,"min":1.0,"max":9.0},"halstead":{"n1":21.0,"N1":142.0,"n2":40.0,"N2":77.0,"length":219.0,"estimated_program_length":305.11578967384844,"purity_ratio":1.3932227838988513,"vocabulary":61.0,"volume":1298.8314769262722,"difficulty":20.2125,"level":0.049474335188620905,"effort":26252.631227372276,"time":1458.479512631793,"bugs":0.2944380756331436},"loc":{"sloc":48.0,"ploc":46.0,"lloc":17.0,"cloc":0.0,"blank":2.0,"sloc_average":8.0,"ploc_average":7.666666666666667,"lloc_average":2.8333333333333335,"cloc_average":0.0,"blank_average":0.3333333333333333,"sloc_min":15.0,"sloc_max":30.0,"cloc_min":0.0,"cloc_max":0.0,"ploc_min":15.0,"ploc_max":29.0,"lloc_min":5.0,"lloc_max":12.0,"blank_min":0.0,"blank_max":1.0},"nom":{"functions":2.0,"closures":3.0,"functions_average":0.3333333333333333,"closures_average":0.5,"total":5.0,"average":0.8333333333333334,"functions_min":0.0,"functions_max":1.0,"closures_min":0.0,"closures_max":1.0},"mi":{"mi_original":67.09659819159512,"mi_sei":22.830015089396767,"mi_visual_studio":39.23777672023107},"abc":{"assignments":0.0,"branches":0.0,"conditions":0.0,"magnitude":0.0,"assignments_average":0.0,"branches_average":0.0,"conditions_average":0.0,"assignments_min":0.0,"assignments_max":0.0,"branches_min":0.0,"branches_max":0.0,"conditions_min":0.0,"conditions_max":0.0}}},{"name":"insert_category","start_line":63,"end_line":70,"kind":"function","spaces":[{"name":"<anonymous>","start_line":67,"end_line":67,"kind":"function","spaces":[],"metrics":{"nargs":{"total_functions":0.0,"total_closures":0.0,"average_functions":0.0,"average_closures":0.0,"total":0.0,"average":0.0,"functions_min":0.0,"functions_max":0.0,"closures_min":0.0,"closures_max":0.0},"nexits":{"sum":0.0,"average":0.0,"min":0.0,"max":0.0},"cognitive":{"sum":0.0,"average":0.0,"min":0.0,"max":0.0},"cyclomatic":{"sum":1.0,"average":1.0,"min":1.0,"max":1.0},"halstead":{"n1":3.0,"N1":5.0,"n2":4.0,"N2":4.0,"length":9.0,"estimated_program_length":12.754887502163468,"purity_ratio":1.4172097224626077,"vocabulary":7.0,"volume":25.26619429851844,"difficulty":1.5,"level":0.6666666666666666,"effort":37.89929144777766,"time":2.1055161915432032,"bugs":0.0037609665632786643},"loc":{"sloc":1.0,"ploc":1.0,"lloc":0.0,"cloc":0.0,"blank":0.0,"sloc_average":1.0,"ploc_average":1.0,"lloc_average":0.0,"cloc_average":0.0,"blank_average":0.0,"sloc_min":1.0,"sloc_max":1.0,"cloc_min":0.0,"cloc_max":0.0,"ploc_min":1.0,"ploc_max":1.0,"lloc_min":0.0,"lloc_max":0.0,"blank_min":0.0,"blank_max":0.0},"nom":{"functions":0.0,"closures":1.0,"functions_average":0.0,"closures_average":1.0,"total":1.0,"average":1.0,"functions_min":0.0,"functions_max":0.0,"closures_min":1.0,"closures_max":1.0},"mi":{"mi_original":153.97676999581998,"mi_sei":146.54249035246173,"mi_visual_studio":90.04489473439764},"abc":{"assignments":0.0,"branches":0.0,"conditions":0.0,"magnitude":0.0,"assignments_average":0.0,"branches_average":0.0,"conditions_average":0.0,"assignments_min":0.0,"assignments_max":0.0,"branches_min":0.0,"branches_max":0.0,"conditions_min":0.0,"conditions_max":0.0}}}],"metrics":{"nargs":{"total_functions":3.0,"total_closures":0.0,"average_functions":3.0,"average_closures":0.0,"total":3.0,"average":1.5,"functions_min":0.0,"functions_max":3.0,"closures_min":0.0,"closures_max":0.0},"nexits":{"sum":1.0,"average":0.5,"min":0.0,"max":1.0},"cognitive":{"sum":1.0,"average":0.5,"min":0.0,"max":1.0},"cyclomatic":{"sum":4.0,"average":2.0,"min":1.0,"max":3.0},"halstead":{"n1":15.0,"N1":30.0,"n2":9.0,"N2":14.0,"length":44.0,"estimated_program_length":87.13268394710859,"purity_ratio":1.9802882715251953,"vocabulary":24.0,"volume":201.73835003173087,"difficulty":11.666666666666666,"level":0.08571428571428572,"effort":2353.614083703527,"time":130.75633798352928,"bugs":0.05897965774575117},"loc":{"sloc":8.0,"ploc":8.0,"lloc":2.0,"cloc":0.0,"blank":0.0,"sloc_average":4.0,"ploc_average":4.0,"lloc_average":1.0,"cloc_average":0.0,"blank_average":0.0,"sloc_min":1.0,"sloc_max":1.0,"cloc_min":0.0,"cloc_max":0.0,"ploc_min":1.0,"ploc_max":1.0,"lloc_min":0.0,"lloc_max":0.0,"blank_min":0.0,"blank_max":0.0},"nom":{"functions":1.0,"closures":1.0,"functions_average":0.5,"closures_average":0.5,"total":2.0,"average":1.0,"functions_min":0.0,"functions_max":1.0,"closures_min":0.0,"closures_max":1.0},"mi":{"mi_original":108.79679490807302,"mi_sei":81.66702392409564,"mi_visual_studio":63.623856671387735},"abc":{"assignments":0.0,"branches":0.0,"conditions":0.0,"magnitude":0.0,"assignments_average":0.0,"branches_average":0.0,"conditions_average":0.0,"assignments_min":0.0,"assignments_max":0.0,"branches_min":0.0,"branches_max":0.0,"conditions_min":0.0,"conditions_max":0.0}}},{"name":"is_yaml_file","start_line":79,"end_line":84,"kind":"function","spaces":[],"metrics":{"nargs":{"total_functions":1.0,"total_closures":0.0,"average_functions":1.0,"average_closures":0.0,"total":1.0,"average":1.0,"functions_min":1.0,"functions_max":1.0,"closures_min":0.0,"closures_max":0.0},"nexits":{"sum":1.0,"average":1.0,"min":1.0,"max":1.0},"cognitive":{"sum":0.0,"average":0.0,"min":0.0,"max":0.0},"cyclomatic":{"sum":1.0,"average":1.0,"min":1.0,"max":1.0},"halstead":{"n1":7.0,"N1":12.0,"n2":10.0,"N2":12.0,"length":24.0,"estimated_program_length":52.87076540327685,"purity_ratio":2.2029485584698687,"vocabulary":17.0,"volume":98.09910819000814,"difficulty":4.2,"level":0.23809523809523808,"effort":412.0162543980342,"time":22.8897919110019,"bugs":0.01845673932137217},"loc":{"sloc":6.0,"ploc":6.0,"lloc":0.0,"cloc":0.0,"blank":0.0,"sloc_average":6.0,"ploc_average":6.0,"lloc_average":0.0,"cloc_average":0.0,"blank_average":0.0,"sloc_min":6.0,"sloc_max":6.0,"cloc_min":0.0,"cloc_max":0.0,"ploc_min":6.0,"ploc_max":6.0,"lloc_min":0.0,"lloc_max":0.0,"blank_min":0.0,"blank_max":0.0},"nom":{"functions":1.0,"closures":0.0,"functions_average":1.0,"closures_average":0.0,"total":1.0,"average":1.0,"functions_min":1.0,"functions_max":1.0,"closures_min":0.0,"closures_max":0.0},"mi":{"mi_original":117.89640956484268,"mi_sei":94.4895332852044,"mi_visual_studio":68.94526875137},"abc":{"assignments":0.0,"branches":0.0,"conditions":0.0,"magnitude":0.0,"assignments_average":0.0,"branches_average":0.0,"conditions_average":0.0,"assignments_min":0.0,"assignments_max":0.0,"branches_min":0.0,"branches_max":0.0,"conditions_min":0.0,"conditions_max":0.0}}},{"name":"category_file_deserialises","start_line":91,"end_line":117,"kind":"function","spaces":[],"metrics":{"nargs":{"total_functions":0.0,"total_closures":0.0,"average_functions":0.0,"average_closures":0.0,"total":0.0,"average":0.0,"functions_min":0.0,"functions_max":0.0,"closures_min":0.0,"closures_max":0.0},"nexits":{"sum":0.0,"average":0.0,"min":0.0,"max":0.0},"cognitive":{"sum":0.0,"average":0.0,"min":0.0,"max":0.0},"cyclomatic":{"sum":1.0,"average":1.0,"min":1.0,"max":1.0},"halstead":{"n1":10.0,"N1":37.0,"n2":26.0,"N2":39.0,"length":76.0,"estimated_program_length":155.430713620542,"purity_ratio":2.045140968691342,"vocabulary":36.0,"volume":392.91430010961574,"difficulty":7.5,"level":0.13333333333333333,"effort":2946.857250822118,"time":163.7142917123399,"bugs":0.06851486574057912},"loc":{"sloc":27.0,"ploc":14.0,"lloc":8.0,"cloc":0.0,"blank":13.0,"sloc_average":27.0,"ploc_average":14.0,"lloc_average":8.0,"cloc_average":0.0,"blank_average":13.0,"sloc_min":27.0,"sloc_max":27.0,"cloc_min":0.0,"cloc_max":0.0,"ploc_min":14.0,"ploc_max":14.0,"lloc_min":8.0,"lloc_max":8.0,"blank_min":13.0,"blank_max":13.0},"nom":{"functions":1.0,"closures":0.0,"functions_average":1.0,"closures_average":0.0,"total":1.0,"average":1.0,"functions_min":1.0,"functions_max":1.0,"closures_min":0.0,"closures_max":0.0},"mi":{"mi_original":86.31476685523478,"mi_sei":48.92685396492597,"mi_visual_studio":50.476471845166536},"abc":{"assignments":0.0,"branches":0.0,"conditions":0.0,"magnitude":0.0,"assignments_average":0.0,"branches_average":0.0,"conditions_average":0.0,"assignments_min":0.0,"assignments_max":0.0,"branches_min":0.0,"branches_max":0.0,"conditions_min":0.0,"conditions_max":0.0}}},{"name":"catalog_rejects_duplicates","start_line":120,"end_line":151,"kind":"function","spaces":[],"metrics":{"nargs":{"total_functions":0.0,"total_closures":0.0,"average_functions":0.0,"average_closures":0.0,"total":0.0,"average":0.0,"functions_min":0.0,"functions_max":0.0,"closures_min":0.0,"closures_max":0.0},"nexits":{"sum":0.0,"average":0.0,"min":0.0,"max":0.0},"cognitive":{"sum":0.0,"average":0.0,"min":0.0,"max":0.0},"cyclomatic":{"sum":1.0,"average":1.0,"min":1.0,"max":1.0},"halstead":{"n1":10.0,"N1":54.0,"n2":22.0,"N2":33.0,"length":87.0,"estimated_program_length":131.32677655889415,"purity_ratio":1.509503178837864,"vocabulary":32.0,"volume":435.0,"difficulty":7.5,"level":0.13333333333333333,"effort":3262.5,"time":181.25,"bugs":0.0733239341718495},"loc":{"sloc":32.0,"ploc":32.0,"lloc":4.0,"cloc":0.0,"blank":0.0,"sloc_average":32.0,"ploc_average":32.0,"lloc_average":4.0,"cloc_average":0.0,"blank_average":0.0,"sloc_min":32.0,"sloc_max":32.0,"cloc_min":0.0,"cloc_max":0.0,"ploc_min":32.0,"ploc_max":32.0,"lloc_min":4.0,"lloc_max":4.0,"blank_min":0.0,"blank_max":0.0},"nom":{"functions":1.0,"closures":0.0,"functions_average":1.0,"closures_average":0.0,"total":1.0,"average":1.0,"functions_min":1.0,"functions_max":1.0,"closures_min":0.0,"closures_max":0.0},"mi":{"mi_original":83.03327901298327,"mi_sei":44.192667728172324,"mi_visual_studio":48.557473107007766},"abc":{"assignments":0.0,"branches":0.0,"conditions":0.0,"magnitude":0.0,"assignments_average":0.0,"branches_average":0.0,"conditions_average":0.0,"assignments_min":0.0,"assignments_max":0.0,"branches_min":0.0,"branches_max":0.0,"conditions_min":0.0,"conditions_max":0.0}}}],"metrics":{"nargs":{"total_functions":5.0,"total_closures":0.0,"average_functions":0.8333333333333334,"average_closures":0.0,"total":5.0,"average":0.5,"functions_min":0.0,"functions_max":3.0,"closures_min":0.0,"closures_max":0.0},"nexits":{"sum":0.0,"average":0.5,"min":0.0,"max":2.0},"cognitive":{"sum":6.0,"average":0.6,"min":0.0,"max":4.0},"cyclomatic":{"sum":25.0,"average":2.0833333333333335,"min":1.0,"max":9.0},"halstead":{"n1":23.0,"N1":328.0,"n2":104.0,"N2":214.0,"length":542.0,"estimated_program_length":800.8876556759848,"purity_ratio":1.4776525012472044,"vocabulary":127.0,"volume":3787.8671002305136,"difficulty":23.66346153846154,"level":0.042259244209670865,"effort":89634.0474391086,"time":4979.669302172701,"bugs":0.6676170461997668},"loc":{"sloc":152.0,"ploc":127.0,"lloc":31.0,"cloc":0.0,"blank":25.0,"sloc_average":12.666666666666666,"ploc_average":10.583333333333334,"lloc_average":2.5833333333333335,"cloc_average":0.0,"blank_average":2.0833333333333335,"sloc_min":6.0,"sloc_max":48.0,"cloc_min":0.0,"cloc_max":0.0,"ploc_min":6.0,"ploc_max":46.0,"lloc_min":0.0,"lloc_max":17.0,"blank_min":0.0,"blank_max":13.0},"nom":{"functions":6.0,"closures":4.0,"functions_average":0.5,"closures_average":0.3333333333333333,"total":10.0,"average":0.8333333333333334,"functions_min":0.0,"functions_max":1.0,"closures_min":0.0,"closures_max":1.0},"mi":{"mi_original":41.01743204206525,"mi_sei":-13.97970970981359,"mi_visual_studio":23.986802363780846},"abc":{"assignments":0.0,"branches":0.0,"conditions":0.0,"magnitude":0.0,"assignments_average":0.0,"branches_average":0.0,"conditions_average":0.0,"assignments_min":0.0,"assignments_max":0.0,"branches_min":0.0,"branches_max":0.0,"conditions_min":0.0,"conditions_max":0.0}}}